reportlab-stubs/METADATA.toml
reportlab-stubs/__init__.pyi
reportlab-stubs/py.typed
reportlab-stubs/rl_config.pyi
reportlab-stubs/rl_settings.pyi
reportlab-stubs/graphics/__init__.pyi
reportlab-stubs/graphics/renderPDF.pyi
reportlab-stubs/graphics/renderPM.pyi
reportlab-stubs/graphics/renderPS.pyi
reportlab-stubs/graphics/renderSVG.pyi
reportlab-stubs/graphics/renderbase.pyi
reportlab-stubs/graphics/shapes.pyi
reportlab-stubs/graphics/svgpath.pyi
reportlab-stubs/graphics/transform.pyi
reportlab-stubs/graphics/utils.pyi
reportlab-stubs/graphics/widgetbase.pyi
reportlab-stubs/graphics/barcode/__init__.pyi
reportlab-stubs/graphics/barcode/code128.pyi
reportlab-stubs/graphics/barcode/code39.pyi
reportlab-stubs/graphics/barcode/code93.pyi
reportlab-stubs/graphics/barcode/common.pyi
reportlab-stubs/graphics/barcode/dmtx.pyi
reportlab-stubs/graphics/barcode/eanbc.pyi
reportlab-stubs/graphics/barcode/ecc200datamatrix.pyi
reportlab-stubs/graphics/barcode/fourstate.pyi
reportlab-stubs/graphics/barcode/lto.pyi
reportlab-stubs/graphics/barcode/qr.pyi
reportlab-stubs/graphics/barcode/qrencoder.pyi
reportlab-stubs/graphics/barcode/usps.pyi
reportlab-stubs/graphics/barcode/usps4s.pyi
reportlab-stubs/graphics/barcode/widgets.pyi
reportlab-stubs/graphics/charts/__init__.pyi
reportlab-stubs/graphics/charts/areas.pyi
reportlab-stubs/graphics/charts/axes.pyi
reportlab-stubs/graphics/charts/barcharts.pyi
reportlab-stubs/graphics/charts/dotbox.pyi
reportlab-stubs/graphics/charts/doughnut.pyi
reportlab-stubs/graphics/charts/legends.pyi
reportlab-stubs/graphics/charts/linecharts.pyi
reportlab-stubs/graphics/charts/lineplots.pyi
reportlab-stubs/graphics/charts/markers.pyi
reportlab-stubs/graphics/charts/piecharts.pyi
reportlab-stubs/graphics/charts/slidebox.pyi
reportlab-stubs/graphics/charts/spider.pyi
reportlab-stubs/graphics/charts/textlabels.pyi
reportlab-stubs/graphics/charts/utils.pyi
reportlab-stubs/graphics/charts/utils3d.pyi
reportlab-stubs/graphics/samples/__init__.pyi
types_reportlab-4.4.9.20260117.dist-info/licenses/LICENSE
types_reportlab-4.4.9.20260117.dist-info/METADATA
types_reportlab-4.4.9.20260117.dist-info/WHEEL
types_reportlab-4.4.9.20260117.dist-info/top_level.txt
types_reportlab-4.4.9.20260117.dist-info/RECORD
